{
  "OldId": "Bblo",
  "NewId": "B026",
  "Unk": [
    0
  ],
  "Modifications": [
    {
      "Id": "frac",
      "Type": 3,
      "Value": "human"
    },
    {
      "Id": "fart",
      "Type": 3,
      "Value": "ReplaceableTextures\\CommandButtons\\BTNFlameWall.blp"
    },
    {
      "Id": "ftip",
      "Type": 3,
      "Value": "Empowerment of the Inferno"
    },
    {
      "Id": "fube",
      "Type": 3,
      "Value": "This unit has been Empowered by the Inferno; its attack rate and movement speed are increased."
    },
    {
      "Id": "ftat",
      "Type": 3,
      "Value": "Abilities\\Spells\\Other\\BreathOfFire\\BreathOfFireDamage.mdl"
    }
  ]
}