{
  "OldId": "ACvs",
  "NewId": "A0SX",
  "Unk": [
    0
  ],
  "Modifications": [
    {
      "Level": 1,
      "Id": "abuf",
      "Type": 3,
      "Value": "B068,B067"
    },
    {
      "Level": 1,
      "Pointer": 1,
      "Id": "Poi1",
      "Type": 2,
      "Value": 0
    },
    {
      "Level": 1,
      "Pointer": 3,
      "Id": "Poi3",
      "Type": 2,
      "Value": 0.5
    },
    {
      "Level": 1,
      "Pointer": 4,
      "Id": "Poi4",
      "Value": 0
    },
    {
      "Level": 1,
      "Id": "adur",
      "Type": 2,
      "Value": 0.5
    },
    {
      "Level": 1,
      "Id": "ahdu",
      "Type": 2,
      "Value": 0.15
    },
    {
      "Id": "arac",
      "Type": 3,
      "Value": "orc"
    },
    {
      "Id": "aart",
      "Type": 3,
      "Value": "ReplaceableTextures\\CommandButtons\\PASEnchantedBlade.blp"
    },
    {
      "Id": "abpx",
      "Value": 2
    },
    {
      "Id": "ansf",
      "Type": 3,
      "Value": "(Teal,Grey) (Raider)"
    },
    {
      "Id": "anam",
      "Type": 3,
      "Value": "Bleeding Blade"
    },
    {
      "Level": 1,
      "Id": "atp1",
      "Type": 3,
      "Value": "Bleeding Blade"
    },
    {
      "Level": 1,
      "Id": "aub1",
      "Type": 3,
      "Value": "Causes this units attacks to reduce attack speed by 50%. |n|cffffcc00Lasts 0.5(0.15) seconds."
    }
  ]
}