{
  "OldId": "AHtb",
  "NewId": "A0XO",
  "Unk": [
    0
  ],
  "Modifications": [
    {
      "Level": 2,
      "Id": "amcs",
      "Value": 175
    },
    {
      "Level": 3,
      "Id": "amcs",
      "Value": 175
    },
    {
      "Level": 4,
      "Id": "amcs",
      "Value": 150
    },
    {
      "Level": 1,
      "Pointer": 1,
      "Id": "Htb1",
      "Type": 2,
      "Value": 400
    },
    {
      "Level": 3,
      "Pointer": 1,
      "Id": "Htb1",
      "Type": 2,
      "Value": 600
    },
    {
      "Level": 4,
      "Pointer": 1,
      "Id": "Htb1",
      "Type": 2,
      "Value": 300
    },
    {
      "Level": 1,
      "Id": "adur",
      "Type": 2,
      "Value": 4
    },
    {
      "Level": 3,
      "Id": "adur",
      "Type": 2,
      "Value": 6
    },
    {
      "Level": 4,
      "Id": "adur",
      "Type": 2,
      "Value": 7
    },
    {
      "Level": 1,
      "Id": "ahdu",
      "Type": 2,
      "Value": 4
    },
    {
      "Level": 2,
      "Id": "ahdu",
      "Type": 2,
      "Value": 5
    },
    {
      "Level": 4,
      "Id": "ahdu",
      "Type": 2,
      "Value": 3.5
    },
    {
      "Level": 1,
      "Id": "aran",
      "Type": 2,
      "Value": 900
    },
    {
      "Level": 2,
      "Id": "aran",
      "Type": 2,
      "Value": 900
    },
    {
      "Level": 3,
      "Id": "aran",
      "Type": 2,
      "Value": 900
    },
    {
      "Level": 4,
      "Id": "aran",
      "Type": 2,
      "Value": 700
    },
    {
      "Level": 2,
      "Pointer": 1,
      "Id": "Htb1",
      "Type": 2,
      "Value": 500
    },
    {
      "Level": 1,
      "Id": "acdn",
      "Type": 2,
      "Value": 30
    },
    {
      "Level": 2,
      "Id": "acdn",
      "Type": 2,
      "Value": 30
    },
    {
      "Level": 3,
      "Id": "acdn",
      "Type": 2,
      "Value": 30
    },
    {
      "Level": 3,
      "Id": "ahdu",
      "Type": 2,
      "Value": 6
    },
    {
      "Level": 1,
      "Id": "amcs",
      "Value": 175
    },
    {
      "Id": "alsk",
      "Value": 5
    },
    {
      "Id": "arlv",
      "Value": 10
    },
    {
      "Id": "ansf",
      "Type": 3,
      "Value": "(Renault)"
    },
    {
      "Id": "ahky",
      "Type": 3,
      "Value": "R"
    },
    {
      "Id": "anam",
      "Type": 3,
      "Value": "Greater Storm Bolt"
    },
    {
      "Id": "arhk",
      "Type": 3,
      "Value": "R"
    },
    {
      "Id": "aret",
      "Type": 3,
      "Value": "Learn Greater Storm Bolt - [|cffffcc00Level %d|r]"
    },
    {
      "Id": "arut",
      "Type": 3,
      "Value": "A magical hammer that is thrown at an enemy unit, causing damage and stunning the target. |n|n|cffffcc00Level 1|r - 400 damage, 4 second stun.|n|cffffcc00Level 2|r - 500 damage, 5 second stun.|n|cffffcc00Level 3|r - 600 damage, 6 second stun."
    },
    {
      "Level": 1,
      "Id": "atp1",
      "Type": 3,
      "Value": "Greater Storm Bolt - [|cffffcc00Level 1|r]"
    },
    {
      "Level": 2,
      "Id": "atp1",
      "Type": 3,
      "Value": "Greater Storm Bolt - [|cffffcc00Level 2|r]"
    },
    {
      "Level": 3,
      "Id": "atp1",
      "Type": 3,
      "Value": "Greater Storm Bolt - [|cffffcc00Level 3|r]"
    },
    {
      "Level": 4,
      "Id": "atp1",
      "Type": 3,
      "Value": "Greater Storm Bolt (|cffffcc00Q|r) - [|cffffcc00Level 4|r]"
    },
    {
      "Level": 1,
      "Id": "aub1",
      "Type": 3,
      "Value": "Throws a magical hammer at a target enemy unit, dealing 400 damage and stunning the target for 4 seconds."
    },
    {
      "Level": 2,
      "Id": "aub1",
      "Type": 3,
      "Value": "Throws a magical hammer at a target enemy unit, dealing 500 damage and stunning the target for 5 seconds."
    },
    {
      "Level": 3,
      "Id": "aub1",
      "Type": 3,
      "Value": "Throws a magical hammer at a target enemy unit, dealing 600 damage and stunning the target for 6 seconds."
    },
    {
      "Level": 4,
      "Id": "aub1",
      "Type": 3,
      "Value": "Throws a magical hammer at a target enemy unit, dealing 400 damage and stunning the target for 7 seconds. Lasts 3.5 seconds on heroes."
    },
    {
      "Id": "abpx",
      "Value": 3
    },
    {
      "Id": "arpx",
      "Value": 3
    }
  ]
}