{
  "OldId": "Absk",
  "NewId": "ZBCP",
  "Unk": [
    0
  ],
  "Modifications": [
    {
      "Level": 1,
      "Pointer": 1,
      "Id": "bsk1",
      "Type": 2,
      "Value": 0
    },
    {
      "Level": 1,
      "Pointer": 2,
      "Id": "bsk2",
      "Type": 2,
      "Value": 0
    },
    {
      "Id": "areq",
      "Type": 3,
      "Value": ""
    },
    {
      "Id": "arac",
      "Type": 3,
      "Value": "undead"
    },
    {
      "Level": 1,
      "Pointer": 3,
      "Id": "bsk3",
      "Type": 2,
      "Value": 0
    },
    {
      "Level": 1,
      "Id": "acdn",
      "Type": 2,
      "Value": 5
    },
    {
      "Level": 1,
      "Id": "ahdu",
      "Type": 2,
      "Value": 0.001
    },
    {
      "Level": 1,
      "Id": "adur",
      "Type": 2,
      "Value": 0.001
    },
    {
      "Level": 1,
      "Id": "abuf",
      "Type": 3,
      "Value": ""
    },
    {
      "Id": "ansf",
      "Type": 3,
      "Value": "(Legion Teleporters)"
    },
    {
      "Id": "ahky",
      "Type": 3,
      "Value": "S"
    },
    {
      "Level": 1,
      "Id": "aub1",
      "Type": 3,
      "Value": "Closes all active portals, enabling a new one to be formed. The Alterac portal, however, takes significantly longer to seal.\r\n"
    },
    {
      "Level": 1,
      "Id": "atp1",
      "Type": 3,
      "Value": "Close Portals"
    },
    {
      "Id": "anam",
      "Type": 3,
      "Value": "Close Portals"
    },
    {
      "Id": "aart",
      "Type": 3,
      "Value": "ReplaceableTextures\\CommandButtons\\BTNPortalBlue.blp"
    },
    {
      "Id": "abpy",
      "Value": 0
    },
    {
      "Id": "abpx",
      "Value": 1
    }
  ]
}