[
  {
    "State": 2,
    "Life": 255,
    "TypeId": 1752387655,
    "Position": {
      "X": -1198.0605,
      "Y": -25907.518,
      "Z": 393.60028
    },
    "Scale": {
      "X": 0.99999994,
      "Y": 0.99999994,
      "Z": 0.99999994
    },
    "SkinId": 1752387655,
    "MapItemTableId": -1,
    "ItemTableSets": [],
    "CreationNumber": 30947
  },
  {
    "State": 6,
    "Life": 255,
    "TypeId": 1802654279,
    "Variation": 2,
    "Position": {
      "X": -1486.0625,
      "Y": -25754.303,
      "Z": 354.82132
    },
    "Rotation": 1.0297444,
    "Scale": {
      "X": 0.99999994,
      "Y": 0.99999994,
      "Z": 0.99999994
    },
    "SkinId": 1802654279,
    "MapItemTableId": -1,
    "ItemTableSets": [],
    "CreationNumber": 31426
  },
  {
    "State": 6,
    "Life": 255,
    "TypeId": 1144008772,
    "Position": {
      "X": -1189.5449,
      "Y": -26048.182,
      "Z": 471.69992
    },
    "Rotation": 4.2011824,
    "Scale": {
      "X": 1.5,
      "Y": 1.5,
      "Z": 1.5
    },
    "SkinId": 1144008772,
    "MapItemTableId": -1,
    "ItemTableSets": [],
    "CreationNumber": 4417
  },
  {
    "State": 2,
    "Life": 255,
    "TypeId": 1936543811,
    "Variation": 3,
    "Position": {
      "X": -1322.9453,
      "Y": -26049.363,
      "Z": 386.57944
    },
    "Rotation": 4.014258,
    "Scale": {
      "X": 0.99999994,
      "Y": 0.99999994,
      "Z": 0.99999994
    },
    "SkinId": 1936543811,
    "MapItemTableId": -1,
    "ItemTableSets": [],
    "CreationNumber": 30929
  },
  {
    "State": 2,
    "Life": 255,
    "TypeId": 1936543811,
    "Variation": 3,
    "Position": {
      "X": -1410.9922,
      "Y": -25995.32,
      "Z": 397.15265
    },
    "Rotation": 4.4680433,
    "Scale": {
      "X": 0.99999994,
      "Y": 0.99999994,
      "Z": 0.99999994
    },
    "SkinId": 1936543811,
    "MapItemTableId": -1,
    "ItemTableSets": [],
    "CreationNumber": 30928
  },
  {
    "State": 2,
    "Life": 255,
    "TypeId": 1936543811,
    "Variation": 1,
    "Position": {
      "X": -1413.2832,
      "Y": -25935.041,
      "Z": 398.39966
    },
    "Rotation": 2.722714,
    "Scale": {
      "X": 0.99999994,
      "Y": 0.99999994,
      "Z": 0.99999994
    },
    "SkinId": 1936543811,
    "MapItemTableId": -1,
    "ItemTableSets": [],
    "CreationNumber": 30927
  },
  {
    "State": 2,
    "Life": 255,
    "TypeId": 1936543811,
    "Variation": 2,
    "Position": {
      "X": -1257.127,
      "Y": -25971.498,
      "Z": 396.27554
    },
    "Rotation": 3.0019667,
    "Scale": {
      "X": 0.99999994,
      "Y": 0.99999994,
      "Z": 0.99999994
    },
    "SkinId": 1936543811,
    "MapItemTableId": -1,
    "ItemTableSets": [],
    "CreationNumber": 30926
  },
  {
    "State": 2,
    "Life": 255,
    "TypeId": 1936543811,
    "Position": {
      "X": -1091.4355,
      "Y": -25650.93,
      "Z": 380.90585
    },
    "Rotation": 3.141593,
    "Scale": {
      "X": 0.99999994,
      "Y": 0.99999994,
      "Z": 0.99999994
    },
    "SkinId": 1936543811,
    "MapItemTableId": -1,
    "ItemTableSets": [],
    "CreationNumber": 30924
  },
  {
    "State": 2,
    "Life": 255,
    "TypeId": 1396060228,
    "Position": {
      "X": -1280,
      "Y": -25728,
      "Z": 400.75
    },
    "Rotation": 4.712389,
    "Scale": {
      "X": 0.99999994,
      "Y": 0.99999994,
      "Z": 0.99999994
    },
    "SkinId": 1396060228,
    "MapItemTableId": -1,
    "ItemTableSets": [],
    "CreationNumber": 4732
  },
  {
    "State": 2,
    "Life": 255,
    "TypeId": 1396060228,
    "Position": {
      "X": -1408,
      "Y": -25856,
      "Z": 400.75
    },
    "Rotation": 4.712389,
    "Scale": {
      "X": 1.8999991,
      "Y": 1.8999991,
      "Z": 1.8999991
    },
    "SkinId": 1396060228,
    "MapItemTableId": -1,
    "ItemTableSets": [],
    "CreationNumber": 4736
  },
  {
    "State": 2,
    "Life": 255,
    "TypeId": 1396060228,
    "Position": {
      "X": -1280,
      "Y": -25856,
      "Z": 400.75
    },
    "Rotation": 4.712389,
    "Scale": {
      "X": 1.2999997,
      "Y": 1.2999997,
      "Z": 1.2999997
    },
    "SkinId": 1396060228,
    "MapItemTableId": -1,
    "ItemTableSets": [],
    "CreationNumber": 8661
  },
  {
    "State": 2,
    "Life": 255,
    "TypeId": 1396060228,
    "Position": {
      "X": -1344,
      "Y": -25984,
      "Z": 400.75
    },
    "Rotation": 4.712389,
    "Scale": {
      "X": 1.1999998,
      "Y": 1.1999998,
      "Z": 1.1999998
    },
    "SkinId": 1396060228,
    "MapItemTableId": -1,
    "ItemTableSets": [],
    "CreationNumber": 8713
  },
  {
    "State": 2,
    "Life": 255,
    "TypeId": 1396060228,
    "Position": {
      "X": -1024,
      "Y": -25600,
      "Z": 400.75
    },
    "Rotation": 4.712389,
    "Scale": {
      "X": 1.2499998,
      "Y": 1.2499998,
      "Z": 0.54999983
    },
    "SkinId": 1396060228,
    "MapItemTableId": -1,
    "ItemTableSets": [],
    "CreationNumber": 11550
  }
]