[
  {
    "State": 2,
    "Life": 255,
    "TypeId": 1479946308,
    "Position": {
      "X": -17664,
      "Y": 8448,
      "Z": 35.25
    },
    "Rotation": 4.712389,
    "Scale": {
      "X": 1.1500001,
      "Y": 1.1500001,
      "Z": 1.1500001
    },
    "SkinId": 1479946308,
    "MapItemTableId": -1,
    "ItemTableSets": [],
    "CreationNumber": 7340
  },
  {
    "State": 2,
    "Life": 255,
    "TypeId": 1802654273,
    "Variation": 5,
    "Position": {
      "X": -17691.2,
      "Y": 8564.566,
      "Z": 18.680439
    },
    "Rotation": 3.3684857,
    "Scale": {
      "X": 0.99999994,
      "Y": 0.99999994,
      "Z": 0.99999994
    },
    "SkinId": 1802654273,
    "MapItemTableId": -1,
    "ItemTableSets": [],
    "CreationNumber": 11963
  },
  {
    "State": 2,
    "Life": 255,
    "TypeId": 1479946308,
    "Position": {
      "X": -17600,
      "Y": 8576,
      "Z": 34
    },
    "Rotation": 4.712389,
    "Scale": {
      "X": 1.0987519,
      "Y": 1.0987519,
      "Z": 1.0987519
    },
    "SkinId": 1479946308,
    "MapItemTableId": -1,
    "ItemTableSets": [],
    "CreationNumber": 7343
  }
]