[
  {
    "TypeId": 1936215873,
    "Variation": 0,
    "Position": {
      "X": -18582.89,
      "Y": 12964.227,
      "Z": -462.009
    },
    "Rotation": 0.6632251,
    "Scale": {
      "X": 4.05,
      "Y": 4.05,
      "Z": 8.85
    },
    "SkinId": 1936215873,
    "State": 6,
    "Life": 255,
    "MapItemTableId": -1,
    "ItemTableSets": [],
    "CreationNumber": 12274
  },
  {
    "TypeId": 1429549124,
    "Variation": 0,
    "Position": {
      "X": -18842.377,
      "Y": 12846.48,
      "Z": 59.2483
    },
    "Rotation": 4.280819,
    "Scale": {
      "X": 2,
      "Y": 2,
      "Z": 2
    },
    "SkinId": 1429549124,
    "State": 2,
    "Life": 255,
    "MapItemTableId": -1,
    "ItemTableSets": [],
    "CreationNumber": 4839
  },
  {
    "TypeId": 1935822913,
    "Variation": 0,
    "Position": {
      "X": -18496.564,
      "Y": 12993.8125,
      "Z": 455.8837
    },
    "Rotation": 1.37881,
    "Scale": {
      "X": 4.3999987,
      "Y": 4.3999987,
      "Z": 4.3999987
    },
    "SkinId": 1935822913,
    "State": 6,
    "Life": 255,
    "MapItemTableId": -1,
    "ItemTableSets": [],
    "CreationNumber": 1681
  },
  {
    "TypeId": 1935822913,
    "Variation": 0,
    "Position": {
      "X": -18936.443,
      "Y": 12590.023,
      "Z": 38.113888
    },
    "Rotation": 6.091199,
    "Scale": {
      "X": 0.95,
      "Y": 0.95,
      "Z": 0.95
    },
    "SkinId": 1935822913,
    "State": 2,
    "Life": 255,
    "MapItemTableId": -1,
    "ItemTableSets": [],
    "CreationNumber": 34322
  },
  {
    "TypeId": 1668306009,
    "Variation": 0,
    "Position": {
      "X": -18816,
      "Y": 12608,
      "Z": 57.875
    },
    "Rotation": 4.712389,
    "Scale": {
      "X": 1,
      "Y": 1,
      "Z": 1
    },
    "SkinId": 1668306009,
    "State": 2,
    "Life": 100,
    "MapItemTableId": -1,
    "ItemTableSets": [],
    "CreationNumber": 34263
  },
  {
    "TypeId": 1668306009,
    "Variation": 0,
    "Position": {
      "X": -18624,
      "Y": 12736,
      "Z": -2.75
    },
    "Rotation": 4.712389,
    "Scale": {
      "X": 1,
      "Y": 1,
      "Z": 1
    },
    "SkinId": 1668306009,
    "State": 2,
    "Life": 100,
    "MapItemTableId": -1,
    "ItemTableSets": [],
    "CreationNumber": 34262
  },
  {
    "TypeId": 1668306009,
    "Variation": 0,
    "Position": {
      "X": -18432,
      "Y": 12928,
      "Z": 121
    },
    "Rotation": 4.712389,
    "Scale": {
      "X": 1,
      "Y": 1,
      "Z": 1
    },
    "SkinId": 1668306009,
    "State": 2,
    "Life": 100,
    "MapItemTableId": -1,
    "ItemTableSets": [],
    "CreationNumber": 34175
  },
  {
    "TypeId": 1668306009,
    "Variation": 0,
    "Position": {
      "X": -18560,
      "Y": 12928,
      "Z": 58
    },
    "Rotation": 4.712389,
    "Scale": {
      "X": 1,
      "Y": 1,
      "Z": 1
    },
    "SkinId": 1668306009,
    "State": 2,
    "Life": 100,
    "MapItemTableId": -1,
    "ItemTableSets": [],
    "CreationNumber": 34172
  }
]