[
  {
    "State": 2,
    "Life": 255,
    "TypeId": 1734498138,
    "Position": {
      "X": -6841.922,
      "Y": 16660.418,
      "Z": 38.399994
    },
    "Rotation": 4.764749,
    "Scale": {
      "X": 0.99999994,
      "Y": 0.99999994,
      "Z": 0.99999994
    },
    "SkinId": 1734498138,
    "MapItemTableId": -1,
    "ItemTableSets": [],
    "CreationNumber": 3050
  },
  {
    "State": 2,
    "Life": 255,
    "TypeId": 1734498121,
    "Position": {
      "X": -6877.5664,
      "Y": 16714.27,
      "Z": 38.399994
    },
    "Rotation": 1.9024088,
    "Scale": {
      "X": 0.99999994,
      "Y": 0.99999994,
      "Z": 0.99999994
    },
    "SkinId": 1734498121,
    "MapItemTableId": -1,
    "ItemTableSets": [],
    "CreationNumber": 3047
  },
  {
    "State": 2,
    "Life": 255,
    "TypeId": 1734498121,
    "Position": {
      "X": -6778.7305,
      "Y": 16984.605,
      "Z": 38.399994
    },
    "Rotation": 0.8552113,
    "Scale": {
      "X": 0.99999994,
      "Y": 0.99999994,
      "Z": 0.99999994
    },
    "SkinId": 1734498121,
    "MapItemTableId": -1,
    "ItemTableSets": [],
    "CreationNumber": 2611
  },
  {
    "State": 2,
    "Life": 255,
    "TypeId": 1734498138,
    "Position": {
      "X": -6800.199,
      "Y": 17028.414,
      "Z": 38.399994
    },
    "Rotation": 0.33161256,
    "Scale": {
      "X": 0.99999994,
      "Y": 0.99999994,
      "Z": 0.99999994
    },
    "SkinId": 1734498138,
    "MapItemTableId": -1,
    "ItemTableSets": [],
    "CreationNumber": 3003
  },
  {
    "State": 2,
    "Life": 255,
    "TypeId": 1734498138,
    "Position": {
      "X": -6850.2734,
      "Y": 16691.484,
      "Z": 38.399994
    },
    "Rotation": 3.1764991,
    "Scale": {
      "X": 0.99999994,
      "Y": 0.99999994,
      "Z": 0.99999994
    },
    "SkinId": 1734498138,
    "MapItemTableId": -1,
    "ItemTableSets": [],
    "CreationNumber": 3044
  },
  {
    "State": 2,
    "Life": 255,
    "TypeId": 1936151106,
    "Position": {
      "X": -6910.373,
      "Y": 16734.438,
      "Z": 22.6894
    },
    "Rotation": 3.0717795,
    "Scale": {
      "X": 0.99999994,
      "Y": 0.99999994,
      "Z": 0.99999994
    },
    "SkinId": 1936151106,
    "MapItemTableId": -1,
    "ItemTableSets": [],
    "CreationNumber": 3260
  },
  {
    "State": 6,
    "Life": 255,
    "TypeId": 1886605890,
    "Variation": 3,
    "Position": {
      "X": -6666.092,
      "Y": 16775.086,
      "Z": 25.468937
    },
    "Rotation": 2.1474905,
    "Scale": {
      "X": 1.3999996,
      "Y": 1.3999996,
      "Z": 1.3999996
    },
    "SkinId": 1886605890,
    "MapItemTableId": -1,
    "ItemTableSets": [],
    "CreationNumber": 3802
  },
  {
    "State": 2,
    "Life": 255,
    "TypeId": 1734498138,
    "Position": {
      "X": -6668.877,
      "Y": 17134.77,
      "Z": 38.399994
    },
    "Rotation": 5.305801,
    "Scale": {
      "X": 0.99999994,
      "Y": 0.99999994,
      "Z": 0.99999994
    },
    "SkinId": 1734498138,
    "MapItemTableId": -1,
    "ItemTableSets": [],
    "CreationNumber": 3049
  },
  {
    "State": 6,
    "Life": 255,
    "TypeId": 1936151106,
    "Variation": 2,
    "Position": {
      "X": -6766.2812,
      "Y": 16970.04,
      "Z": 20.040276
    },
    "Rotation": 3.0717795,
    "Scale": {
      "X": 0.99999994,
      "Y": 0.99999994,
      "Z": 1.4499996
    },
    "SkinId": 1936151106,
    "MapItemTableId": -1,
    "ItemTableSets": [],
    "CreationNumber": 1801
  }
]