[
  {
    "TypeId": 1650874190,
    "Variation": 0,
    "Position": {
      "X": -8377.41,
      "Y": -10897.789,
      "Z": 38.399994
    },
    "Rotation": 1.0297443,
    "Scale": {
      "X": 0.5999999,
      "Y": 0.5999999,
      "Z": 0.5999999
    },
    "SkinId": 1650874190,
    "State": 2,
    "Life": 255,
    "MapItemTableId": -1,
    "ItemTableSets": [],
    "CreationNumber": 23696
  },
  {
    "TypeId": 1885755214,
    "Variation": 0,
    "Position": {
      "X": -8374.035,
      "Y": -10781.633,
      "Z": 38.399994
    },
    "Rotation": 1.3089969,
    "Scale": {
      "X": 0.6999999,
      "Y": 0.6999999,
      "Z": 0.6999999
    },
    "SkinId": 1885755214,
    "State": 2,
    "Life": 255,
    "MapItemTableId": -1,
    "ItemTableSets": [],
    "CreationNumber": 23697
  },
  {
    "TypeId": 829706060,
    "Variation": 0,
    "Position": {
      "X": -8499.734,
      "Y": -10982.152,
      "Z": 77.29895
    },
    "Rotation": 2.5481806,
    "Scale": {
      "X": 1,
      "Y": 1,
      "Z": 1
    },
    "SkinId": 829706060,
    "State": 2,
    "Life": 255,
    "MapItemTableId": -1,
    "ItemTableSets": [],
    "CreationNumber": 23700
  },
  {
    "TypeId": 829706060,
    "Variation": 0,
    "Position": {
      "X": -8619.137,
      "Y": -10934.191,
      "Z": 67.80561
    },
    "Rotation": 4.2236967,
    "Scale": {
      "X": 1,
      "Y": 1,
      "Z": 1
    },
    "SkinId": 829706060,
    "State": 2,
    "Life": 255,
    "MapItemTableId": -1,
    "ItemTableSets": [],
    "CreationNumber": 23701
  }
]