[
  {
    "State": 2,
    "Life": 100,
    "TypeId": 1668052057,
    "Position": {
      "X": 14080,
      "Y": -3776,
      "Z": 716.125
    },
    "Rotation": 4.712389,
    "Scale": {
      "X": 1,
      "Y": 1,
      "Z": 1
    },
    "SkinId": 1668052057,
    "MapItemTableId": -1,
    "ItemTableSets": [],
    "CreationNumber": 29758
  },
  {
    "State": 2,
    "Life": 100,
    "TypeId": 1668052057,
    "Position": {
      "X": 14208,
      "Y": -3776,
      "Z": 714
    },
    "Rotation": 4.712389,
    "Scale": {
      "X": 1,
      "Y": 1,
      "Z": 1
    },
    "SkinId": 1668052057,
    "MapItemTableId": -1,
    "ItemTableSets": [],
    "CreationNumber": 29757
  },
  {
    "State": 2,
    "Life": 100,
    "TypeId": 1668052057,
    "Position": {
      "X": 14336,
      "Y": -3776,
      "Z": 716
    },
    "Rotation": 4.712389,
    "Scale": {
      "X": 1,
      "Y": 1,
      "Z": 1
    },
    "SkinId": 1668052057,
    "MapItemTableId": -1,
    "ItemTableSets": [],
    "CreationNumber": 29756
  },
  {
    "State": 2,
    "Life": 100,
    "TypeId": 1668052057,
    "Position": {
      "X": 14464,
      "Y": -3776,
      "Z": 672.625
    },
    "Rotation": 4.712389,
    "Scale": {
      "X": 1,
      "Y": 1,
      "Z": 1
    },
    "SkinId": 1668052057,
    "MapItemTableId": -1,
    "ItemTableSets": [],
    "CreationNumber": 29755
  },
  {
    "State": 6,
    "Life": 255,
    "TypeId": 942682180,
    "Variation": 8,
    "Position": {
      "X": 14590.613,
      "Y": -3836.7793,
      "Z": 224.84329
    },
    "Rotation": 5.3744826,
    "Scale": {
      "X": 1.9620004,
      "Y": 1.9620004,
      "Z": 2.1620007
    },
    "SkinId": 942682180,
    "MapItemTableId": -1,
    "ItemTableSets": [],
    "CreationNumber": 24133
  },
  {
    "State": 6,
    "Life": 255,
    "TypeId": 1802654284,
    "Variation": 8,
    "Position": {
      "X": 14137.031,
      "Y": -3967.6465,
      "Z": 647.7458
    },
    "Rotation": 5.0090947,
    "Scale": {
      "X": 1,
      "Y": 1,
      "Z": 1
    },
    "SkinId": 1802654284,
    "MapItemTableId": -1,
    "ItemTableSets": [],
    "CreationNumber": 24928
  },
  {
    "State": 6,
    "Life": 255,
    "TypeId": 1802654284,
    "Variation": 8,
    "Position": {
      "X": 14257.008,
      "Y": -3967.0234,
      "Z": 629.7885
    },
    "Rotation": 5.0090947,
    "Scale": {
      "X": 1,
      "Y": 1,
      "Z": 1
    },
    "SkinId": 1802654284,
    "MapItemTableId": -1,
    "ItemTableSets": [],
    "CreationNumber": 24927
  },
  {
    "State": 6,
    "Life": 255,
    "TypeId": 1802654284,
    "Variation": 8,
    "Position": {
      "X": 14363.996,
      "Y": -3962.3145,
      "Z": 610.8781
    },
    "Rotation": 5.0090947,
    "Scale": {
      "X": 1,
      "Y": 1,
      "Z": 1
    },
    "SkinId": 1802654284,
    "MapItemTableId": -1,
    "ItemTableSets": [],
    "CreationNumber": 24926
  },
  {
    "State": 2,
    "Life": 100,
    "TypeId": 1668052057,
    "Position": {
      "X": 14400,
      "Y": -3968,
      "Z": 673.375
    },
    "Rotation": 4.712389,
    "Scale": {
      "X": 1,
      "Y": 1,
      "Z": 1
    },
    "SkinId": 1668052057,
    "MapItemTableId": -1,
    "ItemTableSets": [],
    "CreationNumber": 24871
  },
  {
    "State": 2,
    "Life": 100,
    "TypeId": 1668052057,
    "Position": {
      "X": 14272,
      "Y": -3968,
      "Z": 697.625
    },
    "Rotation": 4.712389,
    "Scale": {
      "X": 1,
      "Y": 1,
      "Z": 1
    },
    "SkinId": 1668052057,
    "MapItemTableId": -1,
    "ItemTableSets": [],
    "CreationNumber": 24872
  },
  {
    "State": 2,
    "Life": 100,
    "TypeId": 1668052057,
    "Position": {
      "X": 14144,
      "Y": -3968,
      "Z": 715.75
    },
    "Rotation": 4.712389,
    "Scale": {
      "X": 1,
      "Y": 1,
      "Z": 1
    },
    "SkinId": 1668052057,
    "MapItemTableId": -1,
    "ItemTableSets": [],
    "CreationNumber": 24873
  },
  {
    "State": 2,
    "Life": 255,
    "TypeId": 1244737604,
    "Position": {
      "X": 14186.766,
      "Y": -4093.7773,
      "Z": 532.57715
    },
    "Rotation": 4.726701,
    "Scale": {
      "X": 2,
      "Y": 1,
      "Z": 1.45
    },
    "SkinId": 1244737604,
    "MapItemTableId": -1,
    "ItemTableSets": [],
    "CreationNumber": 24897
  },
  {
    "State": 2,
    "Life": 255,
    "TypeId": 1953256281,
    "Position": {
      "X": 14416.891,
      "Y": -4088.373,
      "Z": 461.8029
    },
    "Rotation": 4.6984944,
    "Scale": {
      "X": 1.4499996,
      "Y": 1.4499996,
      "Z": 1.6999993
    },
    "SkinId": 1953256281,
    "MapItemTableId": -1,
    "ItemTableSets": [],
    "CreationNumber": 24913
  }
]