[
  {
    "State": 2,
    "Life": 255,
    "TypeId": 842477636,
    "Position": {
      "X": 1344,
      "Y": -9408,
      "Z": 99.8125
    },
    "Rotation": 4.712389,
    "Scale": {
      "X": 1,
      "Y": 1,
      "Z": 1
    },
    "SkinId": 842477636,
    "MapItemTableId": -1,
    "ItemTableSets": [],
    "CreationNumber": 38601
  },
  {
    "State": 2,
    "Life": 255,
    "TypeId": 825700420,
    "Position": {
      "X": 1568,
      "Y": -9504,
      "Z": 89.625
    },
    "Rotation": 4.712389,
    "Scale": {
      "X": 1,
      "Y": 1,
      "Z": 1
    },
    "SkinId": 825700420,
    "MapItemTableId": -1,
    "ItemTableSets": [],
    "CreationNumber": 12991
  },
  {
    "State": 2,
    "Life": 255,
    "TypeId": 2002997324,
    "Position": {
      "X": 1675.1992,
      "Y": -9439.381,
      "Z": 110.07091
    },
    "Rotation": 0.6457718,
    "Scale": {
      "X": 1,
      "Y": 1,
      "Z": 1
    },
    "SkinId": 2002997324,
    "MapItemTableId": -1,
    "ItemTableSets": [],
    "CreationNumber": 38730
  },
  {
    "State": 6,
    "Life": 255,
    "TypeId": 1144008772,
    "Position": {
      "X": 1293.2246,
      "Y": -9376.238,
      "Z": 158.994
    },
    "Rotation": 5.6079173,
    "Scale": {
      "X": 1.999999,
      "Y": 1.999999,
      "Z": 1
    },
    "SkinId": 1144008772,
    "MapItemTableId": -1,
    "ItemTableSets": [],
    "CreationNumber": 12982
  },
  {
    "State": 2,
    "Life": 255,
    "TypeId": 2002997324,
    "Position": {
      "X": 1295.9199,
      "Y": -9458.398,
      "Z": 118.35731
    },
    "Rotation": 3.0019662,
    "Scale": {
      "X": 1,
      "Y": 1,
      "Z": 1
    },
    "SkinId": 2002997324,
    "MapItemTableId": -1,
    "ItemTableSets": [],
    "CreationNumber": 38725
  }
]