[
  {
    "State": 2,
    "Life": 255,
    "TypeId": 842477636,
    "Position": {
      "X": 19840,
      "Y": -28032,
      "Z": 58.5
    },
    "Rotation": 4.712389,
    "Scale": {
      "X": 1,
      "Y": 1,
      "Z": 1
    },
    "SkinId": 842477636,
    "MapItemTableId": -1,
    "ItemTableSets": [],
    "CreationNumber": 8534
  },
  {
    "State": 2,
    "Life": 100,
    "TypeId": 2004112462,
    "Position": {
      "X": 20160,
      "Y": -27968,
      "Z": 43.375
    },
    "Rotation": 2.4958208,
    "Scale": {
      "X": 1,
      "Y": 1,
      "Z": 1
    },
    "SkinId": 2004112462,
    "MapItemTableId": -1,
    "ItemTableSets": [],
    "CreationNumber": 8529
  },
  {
    "State": 2,
    "Life": 100,
    "TypeId": 2004112462,
    "Position": {
      "X": 20096,
      "Y": -27904,
      "Z": -26.25
    },
    "Rotation": 1.6057029,
    "Scale": {
      "X": 1,
      "Y": 1,
      "Z": 1
    },
    "SkinId": 2004112462,
    "MapItemTableId": -1,
    "ItemTableSets": [],
    "CreationNumber": 8528
  },
  {
    "State": 2,
    "Life": 255,
    "TypeId": 842477636,
    "Position": {
      "X": 20160,
      "Y": -27776,
      "Z": -87.5
    },
    "Rotation": 4.712389,
    "Scale": {
      "X": 1,
      "Y": 1,
      "Z": 1
    },
    "SkinId": 842477636,
    "MapItemTableId": -1,
    "ItemTableSets": [],
    "CreationNumber": 8527
  },
  {
    "State": 2,
    "Life": 255,
    "TypeId": 2002997324,
    "Position": {
      "X": 19909.48,
      "Y": -28136.463,
      "Z": 96.68875
    },
    "Rotation": 4.0317106,
    "Scale": {
      "X": 1,
      "Y": 1,
      "Z": 1
    },
    "SkinId": 2002997324,
    "MapItemTableId": -1,
    "ItemTableSets": [],
    "CreationNumber": 7026
  },
  {
    "State": 2,
    "Life": 255,
    "TypeId": 2002997324,
    "Position": {
      "X": 20031.676,
      "Y": -28157.219,
      "Z": 106.59881
    },
    "Rotation": 3.3510323,
    "Scale": {
      "X": 1,
      "Y": 1,
      "Z": 1
    },
    "SkinId": 2002997324,
    "MapItemTableId": -1,
    "ItemTableSets": [],
    "CreationNumber": 7019
  },
  {
    "State": 2,
    "Life": 255,
    "TypeId": 2002997324,
    "Variation": 1,
    "Position": {
      "X": 20003.723,
      "Y": -28055.578,
      "Z": 67.18387
    },
    "Rotation": 0.38397244,
    "Scale": {
      "X": 1,
      "Y": 1,
      "Z": 1
    },
    "SkinId": 2002997324,
    "MapItemTableId": -1,
    "ItemTableSets": [],
    "CreationNumber": 7018
  }
]