[
  {
    "State": 2,
    "Life": 100,
    "TypeId": 1127231554,
    "Variation": 2,
    "Position": {
      "X": 4800,
      "Y": -13696,
      "Z": 63.625
    },
    "Rotation": 2.9670596,
    "Scale": {
      "X": 1,
      "Y": 1,
      "Z": 1
    },
    "SkinId": 1127231554,
    "MapItemTableId": -1,
    "ItemTableSets": [],
    "CreationNumber": 3272
  },
  {
    "State": 2,
    "Life": 100,
    "TypeId": 1953256524,
    "Variation": 7,
    "Position": {
      "X": 4800,
      "Y": -13568,
      "Z": 50
    },
    "Rotation": 2.6179938,
    "Scale": {
      "X": 1,
      "Y": 1,
      "Z": 1
    },
    "SkinId": 1953256524,
    "MapItemTableId": -1,
    "ItemTableSets": [],
    "CreationNumber": 23622
  },
  {
    "State": 2,
    "Life": 100,
    "TypeId": 1953256524,
    "Position": {
      "X": 4544,
      "Y": -13696,
      "Z": 50
    },
    "Rotation": 1.5707964,
    "Scale": {
      "X": 1,
      "Y": 1,
      "Z": 1
    },
    "SkinId": 1953256524,
    "MapItemTableId": -1,
    "ItemTableSets": [],
    "CreationNumber": 16013
  },
  {
    "State": 2,
    "Life": 100,
    "TypeId": 1953256524,
    "Variation": 5,
    "Position": {
      "X": 4672,
      "Y": -13696,
      "Z": 50
    },
    "Rotation": 1.5707964,
    "Scale": {
      "X": 1,
      "Y": 1,
      "Z": 1
    },
    "SkinId": 1953256524,
    "MapItemTableId": -1,
    "ItemTableSets": [],
    "CreationNumber": 15563
  },
  {
    "State": 2,
    "Life": 100,
    "TypeId": 1953256524,
    "Variation": 2,
    "Position": {
      "X": 4672,
      "Y": -13568,
      "Z": 50
    },
    "Rotation": 1.5707964,
    "Scale": {
      "X": 1,
      "Y": 1,
      "Z": 1
    },
    "SkinId": 1953256524,
    "MapItemTableId": -1,
    "ItemTableSets": [],
    "CreationNumber": 7578
  }
]