{
  "OldId": 1718829889,
  "NewId": 1465528385,
  "Unk": [
    0
  ],
  "Modifications": [
    {
      "Id": 1953653089,
      "Type": 3,
      "Value": "ReplaceableTextures/CommandButtons/BTNProwl.blp"
    },
    {
      "Id": 2020631137,
      "Value": 1
    },
    {
      "Id": 1718840929,
      "Type": 3,
      "Value": "TRIGSTR_21144"
    },
    {
      "Id": 2037082209,
      "Type": 3,
      "Value": "TRIGSTR_18542"
    },
    {
      "Id": 1835101793,
      "Type": 3,
      "Value": "TRIGSTR_15003"
    },
    {
      "Level": 1,
      "Id": 829453409,
      "Type": 3,
      "Value": "TRIGSTR_20832"
    },
    {
      "Level": 1,
      "Id": 828536161,
      "Type": 3,
      "Value": "TRIGSTR_20833"
    }
  ]
}