{
  "OldId": 1635021633,
  "NewId": 944386113,
  "Unk": [
    0
  ],
  "Modifications": [
    {
      "Id": 1953653089,
      "Type": 3,
      "Value": "ReplaceableTextures\\CommandButtons\\BTNGoblinLandMine.blp"
    },
    {
      "Id": 2020631137,
      "Value": ""
    },
    {
      "Id": 1718840929,
      "Type": 3,
      "Value": "(Ironforge - engineer)"
    },
    {
      "Id": 2037082209,
      "Type": 3,
      "Value": "R"
    },
    {
      "Id": 1835101793,
      "Type": 3,
      "Value": "Stun Mine"
    },
    {
      "Level": 1,
      "Pointer": 1,
      "Id": 829453409,
      "Type": 3,
      "Value": "Stun Mine"
    },
    {
      "Level": 1,
      "Pointer": 1,
      "Id": 828536161,
      "Type": 3,
      "Value": "Summons an invisible and immovable mine that stuns enemy land units around it. The mine activates when an enemy land unit approaches and destroys all other stun mines in its area of effect. |nThe mine lasts 60 seconds. |nThe stun lasts 4 seconds."
    }
  ]
}