[
  {
    "TypeId": 2003329902,
    "Variation": 0,
    "Position": {
      "X": 1319.0264,
      "Y": -28901.193,
      "Z": 529.43884
    },
    "Rotation": 5.379731,
    "Scale": {
      "X": 1,
      "Y": 1,
      "Z": 1
    },
    "SkinId": 2003329902,
    "Flags": 2,
    "OwnerId": 24,
    "Unk1": 0,
    "Unk2": 0,
    "HP": -1,
    "MP": -1,
    "MapItemTableId": -1,
    "ItemTableSets": [],
    "GoldAmount": 0,
    "TargetAcquisition": -2,
    "HeroLevel": 1,
    "HeroStrength": 0,
    "HeroAgility": 0,
    "HeroIntelligence": 0,
    "InventoryData": [],
    "AbilityData": [],
    "RandomDataMode": 0,
    "RandomData": {
      "Level": 1,
      "Class": 0
    },
    "CustomPlayerColorId": -1,
    "WaygateDestinationRegionId": -1,
    "CreationNumber": 1567
  },
  {
    "TypeId": 1430466670,
    "Variation": 0,
    "Position": {
      "X": 1344,
      "Y": -29056,
      "Z": 533.375
    },
    "Rotation": 4.712389,
    "Scale": {
      "X": 1,
      "Y": 1,
      "Z": 1
    },
    "SkinId": 1430466670,
    "Flags": 2,
    "OwnerId": 24,
    "Unk1": 0,
    "Unk2": 0,
    "HP": -1,
    "MP": -1,
    "MapItemTableId": -1,
    "ItemTableSets": [],
    "GoldAmount": 0,
    "TargetAcquisition": -1,
    "HeroLevel": 1,
    "HeroStrength": 0,
    "HeroAgility": 0,
    "HeroIntelligence": 0,
    "InventoryData": [],
    "AbilityData": [],
    "RandomDataMode": 0,
    "RandomData": {
      "Level": 1,
      "Class": 0
    },
    "CustomPlayerColorId": -1,
    "WaygateDestinationRegionId": -1,
    "CreationNumber": 2538
  },
  {
    "TypeId": 1734894446,
    "Variation": 0,
    "Position": {
      "X": 1438.4811,
      "Y": -29031.938,
      "Z": 533.10455
    },
    "Rotation": 5.3119173,
    "Scale": {
      "X": 1,
      "Y": 1,
      "Z": 1
    },
    "SkinId": 1734894446,
    "Flags": 2,
    "OwnerId": 24,
    "Unk1": 0,
    "Unk2": 0,
    "HP": -1,
    "MP": -1,
    "MapItemTableId": -1,
    "ItemTableSets": [],
    "GoldAmount": 0,
    "TargetAcquisition": -2,
    "HeroLevel": 1,
    "HeroStrength": 0,
    "HeroAgility": 0,
    "HeroIntelligence": 0,
    "InventoryData": [],
    "AbilityData": [],
    "RandomDataMode": 0,
    "RandomData": {
      "Level": 1,
      "Class": 0
    },
    "CustomPlayerColorId": -1,
    "WaygateDestinationRegionId": -1,
    "CreationNumber": 1564
  }
]