{
  "OldId": 1852336449,
  "NewId": 1347235905,
  "Unk": [
    0
  ],
  "Modifications": [
    {
      "Level": 1,
      "Pointer": 1,
      "Id": 829845097,
      "Value": 1
    },
    {
      "Level": 1,
      "Pointer": 2,
      "Id": 846622313,
      "Value": 0
    },
    {
      "Level": 1,
      "Pointer": 3,
      "Id": 863399529,
      "Value": 1
    },
    {
      "Level": 1,
      "Pointer": 4,
      "Id": 880176745,
      "Value": 0
    },
    {
      "Level": 1,
      "Pointer": 5,
      "Id": 896953961,
      "Value": 0
    },
    {
      "Id": 1902473825,
      "Type": 3,
      "Value": ""
    }
  ]
}