[
  {
    "TypeId": 875835503,
    "Variation": 0,
    "Position": {
      "X": -11424,
      "Y": -12448,
      "Z": 623.2812
    },
    "Rotation": 4.712389,
    "Scale": {
      "X": 1,
      "Y": 1,
      "Z": 1
    },
    "SkinId": 875835503,
    "Flags": 2,
    "OwnerId": 27,
    "Unk1": 0,
    "Unk2": 0,
    "HP": -1,
    "MP": -1,
    "MapItemTableId": -1,
    "ItemTableSets": [],
    "GoldAmount": 0,
    "TargetAcquisition": -1,
    "HeroLevel": 1,
    "HeroStrength": 0,
    "HeroAgility": 0,
    "HeroIntelligence": 0,
    "InventoryData": [],
    "AbilityData": [],
    "RandomDataMode": -1,
    "CustomPlayerColorId": -1,
    "WaygateDestinationRegionId": -1,
    "CreationNumber": 1283
  },
  {
    "TypeId": 1752458350,
    "Variation": 0,
    "Position": {
      "X": -11615.178,
      "Y": -12529.898,
      "Z": 610.2873
    },
    "Rotation": 4.6631703,
    "Scale": {
      "X": 1,
      "Y": 1,
      "Z": 1
    },
    "SkinId": 1752458350,
    "Flags": 2,
    "OwnerId": 24,
    "Unk1": 0,
    "Unk2": 0,
    "HP": -1,
    "MP": -1,
    "MapItemTableId": -1,
    "ItemTableSets": [],
    "GoldAmount": 0,
    "TargetAcquisition": -2,
    "HeroLevel": 1,
    "HeroStrength": 0,
    "HeroAgility": 0,
    "HeroIntelligence": 0,
    "InventoryData": [],
    "AbilityData": [
      {
        "AbilityId": 845704769,
        "IsAutocastActive": true,
        "HeroAbilityLevel": 0
      }
    ],
    "RandomDataMode": -1,
    "CustomPlayerColorId": -1,
    "WaygateDestinationRegionId": -1,
    "CreationNumber": 1737
  },
  {
    "TypeId": 1920230510,
    "Variation": 0,
    "Position": {
      "X": -11381.453,
      "Y": -12662.635,
      "Z": 589.25
    },
    "Rotation": 4.5197043,
    "Scale": {
      "X": 1,
      "Y": 1,
      "Z": 1
    },
    "SkinId": 1920230510,
    "Flags": 2,
    "OwnerId": 24,
    "Unk1": 0,
    "Unk2": 0,
    "HP": -1,
    "MP": -1,
    "MapItemTableId": -1,
    "ItemTableSets": [],
    "GoldAmount": 0,
    "TargetAcquisition": -2,
    "HeroLevel": 1,
    "HeroStrength": 0,
    "HeroAgility": 0,
    "HeroIntelligence": 0,
    "InventoryData": [],
    "AbilityData": [],
    "RandomDataMode": -1,
    "CustomPlayerColorId": -1,
    "WaygateDestinationRegionId": -1,
    "CreationNumber": 801
  }
]