[
  {
    "TypeId": 942813295,
    "Variation": 0,
    "Position": {
      "X": -11328,
      "Y": -8960,
      "Z": 37.5
    },
    "Rotation": 4.712389,
    "Scale": {
      "X": 1,
      "Y": 1,
      "Z": 1
    },
    "SkinId": 942813295,
    "Flags": 2,
    "OwnerId": 27,
    "Unk1": 0,
    "Unk2": 0,
    "HP": -1,
    "MP": -1,
    "MapItemTableId": -1,
    "ItemTableSets": [],
    "GoldAmount": 0,
    "TargetAcquisition": -1,
    "HeroLevel": 1,
    "HeroStrength": 0,
    "HeroAgility": 0,
    "HeroIntelligence": 0,
    "InventoryData": [],
    "AbilityData": [],
    "RandomDataMode": -1,
    "CustomPlayerColorId": -1,
    "WaygateDestinationRegionId": -1,
    "CreationNumber": 3281
  },
  {
    "TypeId": 1279340654,
    "Variation": 0,
    "Position": {
      "X": -11520,
      "Y": -8768,
      "Z": 33.562515
    },
    "Rotation": 4.712389,
    "Scale": {
      "X": 1,
      "Y": 1,
      "Z": 1
    },
    "SkinId": 1279340654,
    "Flags": 2,
    "OwnerId": 27,
    "Unk1": 0,
    "Unk2": 0,
    "HP": -1,
    "MP": -1,
    "MapItemTableId": -1,
    "ItemTableSets": [],
    "GoldAmount": 0,
    "TargetAcquisition": -1,
    "HeroLevel": 1,
    "HeroStrength": 0,
    "HeroAgility": 0,
    "HeroIntelligence": 0,
    "InventoryData": [],
    "AbilityData": [],
    "RandomDataMode": -1,
    "CustomPlayerColorId": -1,
    "WaygateDestinationRegionId": -1,
    "CreationNumber": 3295
  },
  {
    "TypeId": 1094135918,
    "Variation": 0,
    "Position": {
      "X": -11265.307,
      "Y": -8825.859,
      "Z": 22.33899
    },
    "Rotation": 2.7771654,
    "Scale": {
      "X": 1,
      "Y": 1,
      "Z": 1
    },
    "SkinId": 1094135918,
    "Flags": 2,
    "OwnerId": 27,
    "Unk1": 0,
    "Unk2": 0,
    "HP": -1,
    "MP": -1,
    "MapItemTableId": -1,
    "ItemTableSets": [],
    "GoldAmount": 0,
    "TargetAcquisition": -1,
    "HeroLevel": 1,
    "HeroStrength": 0,
    "HeroAgility": 0,
    "HeroIntelligence": 0,
    "InventoryData": [],
    "AbilityData": [],
    "RandomDataMode": -1,
    "CustomPlayerColorId": -1,
    "WaygateDestinationRegionId": -1,
    "CreationNumber": 3367
  },
  {
    "TypeId": 942813295,
    "Variation": 0,
    "Position": {
      "X": -11392,
      "Y": -8704,
      "Z": 40.684334
    },
    "Rotation": 4.712389,
    "Scale": {
      "X": 1,
      "Y": 1,
      "Z": 1
    },
    "SkinId": 942813295,
    "Flags": 2,
    "OwnerId": 27,
    "Unk1": 0,
    "Unk2": 0,
    "HP": -1,
    "MP": -1,
    "MapItemTableId": -1,
    "ItemTableSets": [],
    "GoldAmount": 0,
    "TargetAcquisition": -1,
    "HeroLevel": 1,
    "HeroStrength": 0,
    "HeroAgility": 0,
    "HeroIntelligence": 0,
    "InventoryData": [],
    "AbilityData": [],
    "RandomDataMode": -1,
    "CustomPlayerColorId": -1,
    "WaygateDestinationRegionId": -1,
    "CreationNumber": 3432
  },
  {
    "TypeId": 942813295,
    "Variation": 0,
    "Position": {
      "X": -11456,
      "Y": -8896,
      "Z": 33.857784
    },
    "Rotation": 4.712389,
    "Scale": {
      "X": 1,
      "Y": 1,
      "Z": 1
    },
    "SkinId": 942813295,
    "Flags": 2,
    "OwnerId": 27,
    "Unk1": 0,
    "Unk2": 0,
    "HP": -1,
    "MP": -1,
    "MapItemTableId": -1,
    "ItemTableSets": [],
    "GoldAmount": 0,
    "TargetAcquisition": -1,
    "HeroLevel": 1,
    "HeroStrength": 0,
    "HeroAgility": 0,
    "HeroIntelligence": 0,
    "InventoryData": [],
    "AbilityData": [],
    "RandomDataMode": -1,
    "CustomPlayerColorId": -1,
    "WaygateDestinationRegionId": -1,
    "CreationNumber": 3436
  }
]