[
  {
    "Flags": 2,
    "OwnerId": 24,
    "Hp": -1,
    "Mp": -1,
    "TargetAcquisition": -2,
    "HeroLevel": 1,
    "InventoryData": [],
    "AbilityData": [],
    "CustomPlayerColorId": -1,
    "WaygateDestinationRegionId": -1,
    "TypeId": 1818652782,
    "Position": {
      "X": 18829.21,
      "Y": -27739.475,
      "Z": 112
    },
    "Rotation": 2.0314362049102783,
    "Scale": {
      "X": 1,
      "Y": 1,
      "Z": 1
    },
    "SkinId": 1818652782,
    "MapItemTableId": -1,
    "ItemTableSets": [],
    "CreationNumber": 269
  }
]