{
  "OldId": 1818321518,
  "NewId": 1413754990,
  "Unk": [
    0
  ],
  "Modifications": [
    {
      "Id": 1718840949,
      "Type": 3,
      "Value": "(nzoth)"
    },
    {
      "Id": 1953458293,
      "Type": 3,
      "Value": "W"
    },
    {
      "Id": 1633907573,
      "Type": 1,
      "Value": 1.2
    },
    {
      "Id": 1835101813,
      "Type": 3,
      "Value": "Tidemistress"
    },
    {
      "Id": 1885959285,
      "Type": 3,
      "Value": "Summon Tidemistress"
    },
    {
      "Id": 1651864693,
      "Type": 3,
      "Value": "The handmaidens of the Queen.|n|cfff5962dAbilities:|r Chain Lightning, Blink, Brilliance Aura, Arcane Combustion, Resistant Skin, Evasion|n|cff99b4d1Can only train 6.|r|n|n|cffffcc00Attacks land units.|r"
    },
    {
      "Id": 2020631157,
      "Value": 1
    },
    {
      "Id": 1818520949,
      "Type": 3,
      "Value": "war3mapImported\\warqueen.mdl"
    },
    {
      "Id": 1868786037,
      "Type": 3,
      "Value": "ReplaceableTextures\\CommandButtons\\BTNNagaSeaWitch.blp"
    },
    {
      "Id": 1684960117,
      "Type": 3,
      "Value": "NagaSiren"
    }
  ]
}