[
  {
    "TypeId": 2004112474,
    "Variation": 4,
    "Position": {
      "X": -3584,
      "Y": 6144,
      "Z": 65.25
    },
    "Rotation": 1.9547689,
    "Scale": {
      "X": 0.95,
      "Y": 0.95,
      "Z": 0.95
    },
    "SkinId": 2004112474,
    "State": 2,
    "Life": 100,
    "MapItemTableId": -1,
    "ItemTableSets": [],
    "CreationNumber": 16546
  },
  {
    "TypeId": 1802654298,
    "Variation": 8,
    "Position": {
      "X": -3695.4863,
      "Y": 6039.784,
      "Z": -12.87748
    },
    "Rotation": 6.1261063,
    "Scale": {
      "X": 0.9,
      "Y": 0.9,
      "Z": 0.9
    },
    "SkinId": 1802654298,
    "State": 2,
    "Life": 255,
    "MapItemTableId": -1,
    "ItemTableSets": [],
    "CreationNumber": 16536
  },
  {
    "TypeId": 1970425946,
    "Variation": 0,
    "Position": {
      "X": -3650.641,
      "Y": 6130.4966,
      "Z": 30.598083
    },
    "Rotation": 6.0039334,
    "Scale": {
      "X": 0.65,
      "Y": 0.65,
      "Z": 0.65
    },
    "SkinId": 1970425946,
    "State": 2,
    "Life": 255,
    "MapItemTableId": -1,
    "ItemTableSets": [],
    "CreationNumber": 16521
  },
  {
    "TypeId": 1634488129,
    "Variation": 0,
    "Position": {
      "X": -3584.292,
      "Y": 5957.2134,
      "Z": 90.44504
    },
    "Rotation": 1.7489834,
    "Scale": {
      "X": 0.44999987,
      "Y": 0.44999987,
      "Z": 0.44999987
    },
    "SkinId": 1634488129,
    "State": 2,
    "Life": 255,
    "MapItemTableId": -1,
    "ItemTableSets": [],
    "CreationNumber": 16523
  },
  {
    "TypeId": 2004112474,
    "Variation": 1,
    "Position": {
      "X": -3584,
      "Y": 6016,
      "Z": 90.75
    },
    "Rotation": 1.0122911,
    "Scale": {
      "X": 0.95,
      "Y": 0.95,
      "Z": 0.95
    },
    "SkinId": 2004112474,
    "State": 2,
    "Life": 100,
    "MapItemTableId": -1,
    "ItemTableSets": [],
    "CreationNumber": 16530
  }
]